README.md
setup.py
TTCF/TTCF.py
TTCF/__init__.py
TTCF/utils.py
TTCF4LAMMPS.egg-info/PKG-INFO
TTCF4LAMMPS.egg-info/SOURCES.txt
TTCF4LAMMPS.egg-info/dependency_links.txt
TTCF4LAMMPS.egg-info/entry_points.txt
TTCF4LAMMPS.egg-info/requires.txt
TTCF4LAMMPS.egg-info/top_level.txt
test/__init__.py
test/test_TTCF.py
test/test_lammps_import.py
test/test_run_TTCF.py
test/test_utils.py