Metadata-Version: 2.1
Name: TTCF4LAMMPS
Version: 1.0.0
Summary: Code to run TTCF function on LAMMPS
Home-page: https://github.com/edwardsmith999/TTCF4LAMMPS
Author: ['Luca Maffioli', 'Edward Smith']
Author-email: lmaffioli@swin.edu.au
License: GPL
Keywords: Molecular Dynamics TTCF Transient Time Correlation Function
Classifier: Development Status :: 3 - Alpha
Classifier: Programming Language :: Python :: 3.11
Requires-Dist: numpy
Requires-Dist: scipy
Requires-Dist: matplotlib
Requires-Dist: mpi4py
Requires-Dist: lammps
